viewflow_extensions/__init__.py
viewflow_extensions/flow_graph.py
viewflow_extensions/sphinx.py
viewflow_extensions/views.py
viewflow_extensions/management/__init__.py
viewflow_extensions/management/commands/__init__.py
viewflow_extensions/management/commands/flow_graph.py
viewflow_extensions-0.2.1.dist-info/DESCRIPTION.rst
viewflow_extensions-0.2.1.dist-info/METADATA
viewflow_extensions-0.2.1.dist-info/RECORD
viewflow_extensions-0.2.1.dist-info/WHEEL
viewflow_extensions-0.2.1.dist-info/metadata.json
viewflow_extensions-0.2.1.dist-info/top_level.txt
