Metadata-Version: 2.0
Name: viewflow-extensions
Version: 0.2.1
Summary: Useful extensions for django-viewflow.
Home-page: https://github.com/Thermondo/viewflow-extensions
Author: Johannes Hoppe, Thermondo GmbH
Author-email: johannes.hoppe@thermondo.de
License: MIT
Download-URL: https://github.com/Thermondo/viewflow-extensions
Platform: UNKNOWN
Classifier: Development Status :: 3 - Alpha
Classifier: Environment :: Web Environment
Classifier: Intended Audience :: Developers
Classifier: License :: OSI Approved :: Apache Software License
Classifier: Operating System :: OS Independent
Classifier: Programming Language :: Python
Classifier: Programming Language :: Python :: 3
Classifier: Framework :: Django
Classifier: Framework :: Django :: 1.8
Classifier: Framework :: Django :: 1.9
